git_pr_branch/__init__.py
git_pr_branch/cli.py
git_pr_branch/commands.py
git_pr_branch/config.py
git_pr_branch/repo.py
git_pr_branch/servers/__init__.py
git_pr_branch/servers/base.py
git_pr_branch/servers/github.py
git_pr_branch/servers/pagure.py
git_pr_branch/tests/__init__.py
git_pr_branch/utils/__init__.py
git_pr_branch/utils/cli.py
git_pr_branch/utils/cmd.py
git_pr_branch/utils/relationship.py
git_pr_branch/utils/setup.py
git_pr_branch-0.1.0.dist-info/LICENSE
git_pr_branch-0.1.0.dist-info/METADATA
git_pr_branch-0.1.0.dist-info/WHEEL
git_pr_branch-0.1.0.dist-info/entry_points.txt
git_pr_branch-0.1.0.dist-info/RECORD
