Metadata-Version: 2.1
Name: git-pr-branch
Version: 0.1.0
Summary: A command line tool to manage the relationship between branches and pull-requests.
Home-page: https://gitlab.com/abompard/git-pr-branch
License: GPL-3.0-or-later
Keywords: git,github
Author: Aurélien Bompard
Author-email: aurelien@bompard.org
Requires-Python: >=3.7,<4.0
Classifier: Development Status :: 2 - Pre-Alpha
Classifier: Environment :: Console
Classifier: Intended Audience :: Developers
Classifier: License :: OSI Approved :: GNU General Public License v3 or later (GPLv3+)
Classifier: Operating System :: POSIX
Classifier: Programming Language :: Python :: 3
Classifier: Programming Language :: Python :: 3.7
Classifier: Programming Language :: Python :: 3.8
Classifier: Programming Language :: Python :: 3.9
Classifier: Programming Language :: Python :: 3.10
Classifier: Programming Language :: Python :: 3.11
Classifier: Programming Language :: Python :: 3.12
Requires-Dist: attrs (>=19.3.0)
Requires-Dist: click (>=8.0.0,<9.0.0)
Requires-Dist: colorama (>=0.4.1,<0.5.0)
Requires-Dist: python-dateutil (>=2.8.0,<3.0.0)
Requires-Dist: requests (>=2.22.0,<3.0.0)
Requires-Dist: tabulate (>=0.8.7,<0.9.0)
Requires-Dist: toml (>=0.10.1,<0.11.0)
Project-URL: Repository, https://gitlab.com/abompard/git-pr-branch
